mnemosyne/__init__.py
mnemosyne/cli.py
mnemosyne/core.py
mnemosyne-0.1.0.dist-info/LICENSE
mnemosyne-0.1.0.dist-info/METADATA
mnemosyne-0.1.0.dist-info/WHEEL
mnemosyne-0.1.0.dist-info/entry_points.txt
mnemosyne-0.1.0.dist-info/top_level.txt
mnemosyne-0.1.0.dist-info/RECORD
