Metadata-Version: 2.2
Name: mnemosyne
Version: 0.1.0
Summary: A Python package for memory-related utilities
Author-email: Laurent-Philippe Albou <laurent.albou@example.com>
License: MIT
Project-URL: Homepage, https://github.com/username/mnemosyne
Project-URL: Bug Tracker, https://github.com/username/mnemosyne/issues
Classifier: Programming Language :: Python :: 3
Classifier: License :: OSI Approved :: MIT License
Classifier: Operating System :: OS Independent
Requires-Python: >=3.7
License-File: LICENSE
